pyleetcode_utils/__init__.py
pyleetcode_utils/datatypes/__init__.py
pyleetcode_utils/datatypes/tree.py
pyleetcode_utils/examples/__init__.py
pyleetcode_utils/examples/tree.py
pyleetcode_utils/exceptions.py
pyleetcode_utils/py.typed
pyleetcode_utils-0.1.3.dist-info/LICENSE
pyleetcode_utils-0.1.3.dist-info/METADATA
pyleetcode_utils-0.1.3.dist-info/WHEEL
pyleetcode_utils-0.1.3.dist-info/RECORD
