Metadata-Version: 2.1
Name: pyleetcode-utils
Version: 0.1.3
Summary: Python Leetcode utilities
Home-page: https://github.com/smokevadim/pyleetcode-utils
License: MIT
Author: Vadim Gazizov
Author-email: i.am.vadim.gazizov@gmail.com
Requires-Python: >=3.9,<4.0
Classifier: Development Status :: 3 - Alpha
Classifier: Intended Audience :: Developers
Classifier: License :: OSI Approved :: MIT License
Classifier: Operating System :: OS Independent
Classifier: Programming Language :: Python :: 3
Classifier: Programming Language :: Python :: 3.9
Classifier: Programming Language :: Python :: 3.10
Classifier: Programming Language :: Python :: 3.11
Classifier: Programming Language :: Python :: 3.12
Classifier: Topic :: Software Development :: Libraries :: Python Modules
Project-URL: Repository, https://github.com/smokevadim/pyleetcode-utils
